{
  "file_info": {
    "name": "Main.java",
    "main_class": "Main",
    "file_type": "entry_point",
    "purpose": "Application entry point for the Spring Boot application",
    "is_entry_point": true,
    "is_exit_point": false
  },
  "dependencies": [
    {
      "target_file": "ApplicationConfiguration.java",
      "target_class": "ApplicationConfiguration",
      "relationship_type": "import",
      "description": "Configuration class for the application"
    },
    {
      "target_file": "MemberRepository.java",
      "target_class": "MemberRepository",
      "relationship_type": "import",
      "description": "Repository interface for member data access"
    },
    {
      "target_file": "MongoAutoConfiguration.java",
      "target_class": "MongoAutoConfiguration",
      "relationship_type": "import",
      "description": "Spring Boot auto-configuration for MongoDB"
    },
    {
      "target_file": "SpringBootServletInitializer.java",
      "target_class": "SpringBootServletInitializer",
      "relationship_type": "extends",
      "description": "Base class for Spring Boot applications"
    },
    {
      "target_file": "LoggerFactory.java",
      "target_class": "LoggerFactory",
      "relationship_type": "import",
      "description": "Logging utility for error handling"
    },
    {
      "target_file": "SpringApplication.java",
      "target_class": "SpringApplication",
      "relationship_type": "import",
      "description": "Spring Boot application runner"
    }
  ],
  "provides_to": []
}